xr_360_camera_streamer/__about__.py
xr_360_camera_streamer/__init__.py
xr_360_camera_streamer/cli.py
xr_360_camera_streamer/sources/__init__.py
xr_360_camera_streamer/sources/base.py
xr_360_camera_streamer/sources/ffmpeg_source.py
xr_360_camera_streamer/sources/gopro_source.py
xr_360_camera_streamer/sources/opencv_source.py
xr_360_camera_streamer/sources/webcam_source.py
xr_360_camera_streamer/sources/youtube_source.py
xr_360_camera_streamer/streaming/__init__.py
xr_360_camera_streamer/streaming/webrtc_server.py
xr_360_camera_streamer/transforms/__init__.py
xr_360_camera_streamer/transforms/base.py
xr_360_camera_streamer/transforms/equilib_transforms.py
xr_360_camera_streamer-0.0.1.dist-info/METADATA
xr_360_camera_streamer-0.0.1.dist-info/WHEEL
xr_360_camera_streamer-0.0.1.dist-info/entry_points.txt
xr_360_camera_streamer-0.0.1.dist-info/licenses/LICENSE
xr_360_camera_streamer-0.0.1.dist-info/RECORD
